<?xml version="1.0" encoding="UTF-8"?>
<!DOCTYPE suite SYSTEM "http://testng.org/testng-1.0.dtd">
<suite configfailurepolicy="continue" thread-count="1" name="Ionboard">
  <listeners>
    <listener class-name="com.hcl.ionboard.listener.TestListener"/>
  </listeners>
  <test thread-count="1" name="PROJECT_Test1">
    <parameter name="browserName" value="chrome"/>
    <classes>
      <class name="com.hcl.ionboard.testscripts.TYSS_IOB_001"/>
    </classes>
  </test> <!-- PROJECT_Test1 -->
</suite> <!-- Ionboard -->
